<?xml version="1.0" encoding="utf-8"?>
<!DOCTYPE hibernate-mapping PUBLIC "-//Hibernate/Hibernate Mapping DTD 3.0//EN"
"http://hibernate.sourceforge.net/hibernate-mapping-3.0.dtd">
<!-- 
    Mapping file autogenerated by MyEclipse Persistence Tools
-->
<hibernate-mapping package="com.sino.elearning.studyrecord.bean">
<!-- 评测试卷表 -->
    <class name="EEvaluationTest" table="E_EVALUATION_TEST">
        <id name="testId" type="java.lang.Long">
            <column name="TEST_ID" precision="22" scale="0" />
            <generator class="assigned" />
        </id>
        <property name="programId" type="java.lang.Long">
            <column name="PROGRAM_ID" precision="22" scale="0">
                <comment>节目ID</comment>
            </column>
        </property>
        <property name="explain" type="java.lang.String">
            <column name="EXPLAIN" length="400">
                <comment>评测说明</comment>
            </column>
        </property>
        <property name="state" type="java.lang.String">
            <column name="STATE" length="1" not-null="true">
                <comment>是否已建立了评测试卷 0：无评测试卷 1：有评测试卷</comment>
            </column>
        </property>
        <property name="userId" type="java.lang.Long">
            <column name="USER_ID" precision="32" scale="0">
                <comment>创建人ID</comment>
            </column>
        </property>
        <property name="userNm" type="java.lang.String">
            <column name="USER_NM" length="50">
                <comment>创建人</comment>
            </column>
        </property>
        <property name="deptId" type="java.lang.Long">
            <column name="DEPT_ID" precision="32" scale="0">
                <comment>创建人部门ID</comment>
            </column>
        </property>
        <property name="deptName" type="java.lang.String">
            <column name="DEPT_NAME" length="50">
                <comment>创建人部门</comment>
            </column>
        </property>
        <property name="creatTime" type="java.lang.String">
            <column name="CREAT_TIME" length="50">
                <comment>创建时间</comment>
            </column>
        </property>
        <property name="programName" type="java.lang.String">
            <column name="PROGRAM_NAME" length="512">
                <comment>课程资源名称</comment>
            </column>
        </property>
        <property name="programType" type="java.lang.String">
            <column name="PROGRAM_TYPE" length="512">
                <comment>课程资源类别</comment>
            </column>
        </property>
        <property name="testState" type="java.lang.String">
            <column name="TEST_STATE" length="1" not-null="true">
                <comment>评测问卷状态 0：未启用 1：已启用 2：停用</comment>
            </column>
        </property>
    </class>
    <!-- 评测试卷问题表 -->
        <class name="EEvaluationTestQuestion" table="E_EVALUATION_TEST_QUESTION">
        <id name="questionId" type="java.lang.Long">
            <column name="QUESTION_ID" precision="22" scale="0" />
            <generator class="assigned" />
        </id>
        <many-to-one name="test" class="EEvaluationTest" fetch="select">
            <column name="TEST_ID" precision="22" scale="0">
                <comment>试卷ID</comment>
            </column>
        </many-to-one>
        <property name="questionTitle" type="java.lang.String">
            <column name="QUESTION_TITLE" length="400">
                <comment>试卷问题题目</comment>
            </column>
        </property>
        <property name="questionType" type="java.lang.String">
            <column name="QUESTION_TYPE" length="1">
                <comment>试卷问题类型 0：单选题 1：多选题</comment>
            </column>
        </property>
    </class>
    <!-- 评测试卷问题选项表 -->
    <class name="ETestQuestionOption" table="E_TEST_QUESTION_OPTION">
        <id name="optionId" type="java.lang.Long">
            <column name="OPTION_ID" precision="22" scale="0" />
            <generator class="assigned" />
        </id>
        <many-to-one name="testQuestion" class="EEvaluationTestQuestion" fetch="select">
            <column name="QUESTION_ID" precision="22" scale="0">
                <comment>试卷问题ID</comment>
            </column>
        </many-to-one>
        <property name="optionContent" type="java.lang.String">
            <column name="OPTION_CONTENT" length="400">
                <comment>选项内容</comment>
            </column>
        </property>
        <property name="rightAnswers" type="java.lang.String">
            <column name="RIGHT_ANSWERS" length="2">
                <comment>是否为正确答案 0：错误答案 1：正确答案</comment>
            </column>
        </property>
    </class>
    <!-- 答题试卷表 -->
     <class name="EEvaluationRecord" table="E_EVALUATION_RECORD">
        <id name="recordId" type="java.lang.Long">
            <column name="RECORD_ID" precision="22" scale="0" />
            <generator class="native"/>
        </id>
        <property name="testId" type="java.lang.Long">
            <column name="TEST_ID" precision="22" scale="0">
                <comment>评测试卷ID</comment>
            </column>
        </property>
        <property name="achievement" type="java.lang.String">
            <column name="ACHIEVEMENT" length="30">
                <comment>总成绩</comment>
            </column>
        </property>
        <property name="recordState" type="java.lang.String">
            <column name="RECORD_STATE" length="2">
                <comment>填写状态 0:保存（未提交）1:提交</comment>
            </column>
        </property>
        <property name="userId" type="java.lang.Long">
            <column name="USER_ID" precision="22" scale="0">
                <comment>答卷人ID</comment>
            </column>
        </property>
        <property name="userNm" type="java.lang.String">
            <column name="USER_NM" length="50">
                <comment>答卷人</comment>
            </column>
        </property>
        <property name="deptId" type="java.lang.Long">
            <column name="DEPT_ID" precision="22" scale="0">
                <comment>答卷人部门ID</comment>
            </column>
        </property>
        <property name="deptName" type="java.lang.String">
            <column name="DEPT_NAME" length="50">
                <comment>答卷人部门</comment>
            </column>
        </property>
        <property name="time" type="java.lang.String">
            <column name="TIME" length="50">
                <comment>答卷时间</comment>
            </column>
        </property>
    </class>
    <!-- 答题试卷问题表 -->
    <class name="EEvaluationAnswer" table="E_EVALUATION_ANSWER">
        <id name="answerRecordId" type="java.lang.Long">
            <column name="ANSWER_RECORD_ID" precision="22" scale="0" />
            <generator class="native"/>
        </id>
        <many-to-one name="Record" class="EEvaluationRecord" fetch="select">
            <column name="RECORD_ID" precision="22" scale="0">
                <comment>评测试卷记录ID</comment>
            </column>
        </many-to-one>
        <property name="questionId" type="java.lang.Long">
            <column name="QUESTION_ID" precision="22" scale="0">
                <comment>问题ID</comment>
            </column>
        </property>
        <property name="answerState" type="java.lang.String">
            <column name="ANSWER_STATE" length="1">
                <comment>答题情况 1：正确 2：错误</comment>
            </column>
        </property>
    </class>
    <!-- 回答问题选择选项表 -->
     <class name="EEvaluationOption" table="E_EVALUATION_OPTION">
        <id name="answerRecOptionId" type="java.lang.Long">
            <column name="ANSWER_REC_OPTION_ID" precision="22" scale="0" />
           <generator class="native"/>
        </id>
        <many-to-one name="answer" class="EEvaluationAnswer" fetch="select">
            <column name="ANSWER_RECORD_ID" precision="22" scale="0">
                <comment>评测试卷答案记录ID</comment>
            </column>
        </many-to-one>
        <property name="optionId" type="java.lang.Long">
            <column name="OPTION_ID" precision="22" scale="0">
                <comment>选择问题选项ID</comment>
            </column>
        </property>
    </class>
</hibernate-mapping>
