<?xml version="1.0" encoding="utf-8"?>
<!DOCTYPE hibernate-mapping PUBLIC "-//Hibernate/Hibernate Mapping DTD 3.0//EN"
"http://hibernate.sourceforge.net/hibernate-mapping-3.0.dtd">
<!-- 
    Mapping file autogenerated by MyEclipse Persistence Tools
-->
<hibernate-mapping>
    <class name="com.sino.elearning.studyrecord.bean.EResultsRecord" table="E_RESULTS_RECORD">
        <id name="resultsId" type="java.lang.Long">
            <column name="RESULTS_ID" precision="22" scale="0" />
            <generator class="native"/>
        </id>
        <property name="programId" type="java.lang.Long">
            <column name="PROGRAM_ID" precision="22" scale="0">
                <comment>视频资源ID</comment>
            </column>
        </property>
         <property name="programName" type="java.lang.String">
            <column name="PROGRAM_NAME" length="400">
                <comment>资源名称</comment>
            </column>
        </property>
        <property name="studyType" type="java.lang.String">
            <column name="STUDY_TYPE" length="1">
                <comment>学习类型 1:个人学习 2:集体学习</comment>
            </column>
        </property>
        <property name="resultsContent" type="java.lang.String">
            <column name="RESULTS_CONTENT" length="500">
                <comment>成效内容</comment>
            </column>
        </property>
        <property name="state" type="java.lang.String">
            <column name="STATE" length="1">
                <comment>状态 0：未审核 1：已审核</comment>
            </column>
        </property>
        <property name="creatUserId" type="java.lang.Long">
            <column name="CREAT_USER_ID" precision="22" scale="0">
                <comment>创建人ID</comment>
            </column>
        </property>
        <property name="userNm" type="java.lang.String">
            <column name="USER_NM" length="50">
                <comment>创建人</comment>
            </column>
        </property>
        <property name="deptId" type="java.lang.Long">
            <column name="DEPT_ID" precision="22" scale="0">
                <comment>部门ID</comment>
            </column>
        </property>
        <property name="deptName" type="java.lang.String">
            <column name="DEPT_NAME" length="50">
                <comment>创建人部门</comment>
            </column>
        </property>
        <property name="creatTime" type="java.lang.String">
            <column name="CREAT_TIME" length="50">
                <comment>创建时间</comment>
            </column>
        </property>
    </class>
</hibernate-mapping>
